aixd_ara/__init__.py
aixd_ara/api.py
aixd_ara/constants.py
aixd_ara/controller.py
aixd_ara/gh_ui.py
aixd_ara/gh_ui_helper.py
aixd_ara/install.py
aixd_ara/shallow_objects.py
aixd_ara/wrappers.py
aixd_ara/components/README.md
aixd_ara/components/__init__.py
aixd_ara/components/ara_/code.py
aixd_ara/components/ara_/icon.png
aixd_ara/components/ara_/metadata.json
aixd_ara/components/ara_DataBool/code.py
aixd_ara/components/ara_DataBool/icon.png
aixd_ara/components/ara_DataBool/metadata.json
aixd_ara/components/ara_DataCat/code.py
aixd_ara/components/ara_DataCat/icon.png
aixd_ara/components/ara_DataCat/metadata.json
aixd_ara/components/ara_DataInt/code.py
aixd_ara/components/ara_DataInt/icon.png
aixd_ara/components/ara_DataInt/metadata.json
aixd_ara/components/ara_DataObjectsNames/code.py
aixd_ara/components/ara_DataObjectsNames/icon.png
aixd_ara/components/ara_DataObjectsNames/metadata.json
aixd_ara/components/ara_DataReal/code.py
aixd_ara/components/ara_DataReal/icon.png
aixd_ara/components/ara_DataReal/metadata.json
aixd_ara/components/ara_DatasetCreate/code.py
aixd_ara/components/ara_DatasetCreate/icon.png
aixd_ara/components/ara_DatasetCreate/metadata.json
aixd_ara/components/ara_DatasetGenerator/code.py
aixd_ara/components/ara_DatasetGenerator/icon.png
aixd_ara/components/ara_DatasetGenerator/metadata.json
aixd_ara/components/ara_DatasetLoad/code.py
aixd_ara/components/ara_DatasetLoad/icon.png
aixd_ara/components/ara_DatasetLoad/metadata.json
aixd_ara/components/ara_DatasetOneSample/code.py
aixd_ara/components/ara_DatasetOneSample/icon.png
aixd_ara/components/ara_DatasetOneSample/metadata.json
aixd_ara/components/ara_DatasetSummary/code.py
aixd_ara/components/ara_DatasetSummary/icon.png
aixd_ara/components/ara_DatasetSummary/metadata.json
aixd_ara/components/ara_DatasetsMerge/code.py
aixd_ara/components/ara_DatasetsMerge/icon.png
aixd_ara/components/ara_DatasetsMerge/metadata.json
aixd_ara/components/ara_Generator/code.py
aixd_ara/components/ara_Generator/icon.png
aixd_ara-0.10.6.dist-info/AUTHORS.md
aixd_ara-0.10.6.dist-info/LICENSE
aixd_ara-0.10.6.dist-info/METADATA
aixd_ara-0.10.6.dist-info/WHEEL
aixd_ara-0.10.6.dist-info/top_level.txt
aixd_ara-0.10.6.dist-info/RECORD
