Metadata-Version: 2.1
Name: aixd-ara
Version: 0.10.6
Summary: Grasshopper plugin for the AIXD toolkit
Home-page: https://github.com/gramaziokohler/aixd_ara
Author: Aleksandra Apolinarska
Author-email: apolinarska@arch.ethz.ch
License: MIT license
Classifier: Development Status :: 4 - Beta
Classifier: Intended Audience :: Developers
Classifier: Topic :: Scientific/Engineering
Classifier: License :: OSI Approved :: MIT License
Classifier: Operating System :: Unix
Classifier: Operating System :: POSIX
Classifier: Operating System :: Microsoft :: Windows
Classifier: Programming Language :: Python
Classifier: Programming Language :: Python :: 3
Classifier: Programming Language :: Python :: 3.8
Classifier: Programming Language :: Python :: 3.9
Classifier: Programming Language :: Python :: 3.10
Classifier: Programming Language :: Python :: Implementation :: CPython
Requires-Python: >=3.8
License-File: LICENSE
License-File: AUTHORS.md
Requires-Dist: aixd==0.13.0
Requires-Dist: compas<3,>2
Requires-Dist: flask
Provides-Extra: dev
Requires-Dist: attrs>=17.4; extra == "dev"
Requires-Dist: black; extra == "dev"
Requires-Dist: bump2version>=1.0.1; extra == "dev"
Requires-Dist: check-manifest>=0.36; extra == "dev"
Requires-Dist: compas-invocations>=1.0.0; extra == "dev"
Requires-Dist: doc8; extra == "dev"
Requires-Dist: flake8; extra == "dev"
Requires-Dist: invoke>=0.14; extra == "dev"
Requires-Dist: isort; extra == "dev"
Requires-Dist: pytest>=6.0; extra == "dev"
Requires-Dist: sphinx-compas2-theme; extra == "dev"
Requires-Dist: twine; extra == "dev"
Requires-Dist: wheel; extra == "dev"
